{"name": "Durfee", "slug": "durfee", "gender": "boys", "rating": -1.152, "net_rank": 193, "total_teams": 358, "wins": 3, "losses": 17, "avg_margin": -15.05, "sos": 11.948, "sos_rank": 50, "sigma": 10.857, "pred_accuracy": 95.0, "schedule": [{"date": "12/12", "opponent": "Bridgewater Raynham", "opp_slug": "bridgewater-raynham", "opp_ma": true, "score": "37\u201389", "margin": -52, "result": "L", "predicted": -30.9, "pred_correct": true}, {"date": "12/16", "opponent": "Dartmouth", "opp_slug": "dartmouth", "opp_ma": true, "score": "53\u201352", "margin": 1, "result": "W", "predicted": 2.7, "pred_correct": true}, {"date": "12/19", "opponent": "Westport", "opp_slug": "westport", "opp_ma": true, "score": "60\u201335", "margin": 25, "result": "W", "predicted": 14.2, "pred_correct": true}, {"date": "12/29", "opponent": "Southeastern RVT", "opp_slug": "southeastern-rvt", "opp_ma": true, "score": "35\u201358", "margin": -23, "result": "L", "predicted": -5.5, "pred_correct": true}, {"date": "12/30", "opponent": "Somerset Berkley Regional", "opp_slug": "somerset-berkley-regional", "opp_ma": true, "score": "54\u201363", "margin": -9, "result": "L", "predicted": -11.8, "pred_correct": true}, {"date": "1/4", "opponent": "Taunton", "opp_slug": "taunton", "opp_ma": true, "score": "66\u201368", "margin": -2, "result": "L", "predicted": -11.2, "pred_correct": true}, {"date": "1/6", "opponent": "Brockton", "opp_slug": "brockton", "opp_ma": true, "score": "36\u201352", "margin": -16, "result": "L", "predicted": -23.3, "pred_correct": true}, {"date": "1/9", "opponent": "Westport", "opp_slug": "westport", "opp_ma": true, "score": "75\u201356", "margin": 19, "result": "W", "predicted": 14.2, "pred_correct": true}, {"date": "1/11", "opponent": "Taunton", "opp_slug": "taunton", "opp_ma": true, "score": "61\u201367", "margin": -6, "result": "L", "predicted": -11.2, "pred_correct": true}, {"date": "1/13", "opponent": "Bishop Stang", "opp_slug": "bishop-stang", "opp_ma": true, "score": "49\u201373", "margin": -24, "result": "L", "predicted": -15.7, "pred_correct": true}, {"date": "1/16", "opponent": "New Bedford", "opp_slug": "new-bedford", "opp_ma": true, "score": "51\u201394", "margin": -43, "result": "L", "predicted": -29.4, "pred_correct": true}, {"date": "1/20", "opponent": "Bridgewater Raynham", "opp_slug": "bridgewater-raynham", "opp_ma": true, "score": "60\u201376", "margin": -16, "result": "L", "predicted": -30.9, "pred_correct": true}, {"date": "1/23", "opponent": "Dartmouth", "opp_slug": "dartmouth", "opp_ma": true, "score": "60\u201364", "margin": -4, "result": "L", "predicted": 2.7, "pred_correct": false}, {"date": "1/31", "opponent": "Everett", "opp_slug": "everett", "opp_ma": true, "score": "57\u201375", "margin": -18, "result": "L", "predicted": -10.9, "pred_correct": true}, {"date": "2/3", "opponent": "Bishop Stang", "opp_slug": "bishop-stang", "opp_ma": true, "score": "39\u201373", "margin": -34, "result": "L", "predicted": -15.7, "pred_correct": true}, {"date": "2/5", "opponent": "Greater New Bedford", "opp_slug": "greater-new-bedford", "opp_ma": true, "score": "68\u201376", "margin": -8, "result": "L", "predicted": -12.6, "pred_correct": true}, {"date": "2/10", "opponent": "Brockton", "opp_slug": "brockton", "opp_ma": true, "score": "47\u201364", "margin": -17, "result": "L", "predicted": -23.3, "pred_correct": true}, {"date": "2/13", "opponent": "New Bedford", "opp_slug": "new-bedford", "opp_ma": true, "score": "38\u201368", "margin": -30, "result": "L", "predicted": -29.4, "pred_correct": true}, {"date": "2/17", "opponent": "Quincy", "opp_slug": "quincy", "opp_ma": true, "score": "53\u201378", "margin": -25, "result": "L", "predicted": -19.1, "pred_correct": true}, {"date": "2/18", "opponent": "Milton", "opp_slug": "milton", "opp_ma": true, "score": "49\u201368", "margin": -19, "result": "L", "predicted": -15.2, "pred_correct": true}]}