{"name": "Saint John's", "slug": "saint-john-s", "gender": "boys", "rating": 23.156, "net_rank": 23, "total_teams": 358, "wins": 13, "losses": 7, "avg_margin": 7.55, "sos": 16.106, "sos_rank": 18, "sigma": 10.857, "pred_accuracy": 85.0, "schedule": [{"date": "12/12", "opponent": "Leominster", "opp_slug": "leominster", "opp_ma": true, "score": "68\u201332", "margin": 36, "result": "W", "predicted": 25.6, "pred_correct": true}, {"date": "12/16", "opponent": "North High", "opp_slug": "north-high", "opp_ma": true, "score": "50\u201330", "margin": 20, "result": "W", "predicted": 17.8, "pred_correct": true}, {"date": "12/23", "opponent": "Millbury", "opp_slug": "millbury", "opp_ma": true, "score": "56\u201340", "margin": 16, "result": "W", "predicted": 4.4, "pred_correct": true}, {"date": "12/27", "opponent": "Wachusett Regional", "opp_slug": "wachusett-regional", "opp_ma": true, "score": "73\u201339", "margin": 34, "result": "W", "predicted": 17.5, "pred_correct": true}, {"date": "12/29", "opponent": "Shrewsbury", "opp_slug": "shrewsbury", "opp_ma": true, "score": "44\u201338", "margin": 6, "result": "W", "predicted": 12.3, "pred_correct": true}, {"date": "1/2", "opponent": "Algonquin", "opp_slug": "algonquin", "opp_ma": true, "score": "58\u201342", "margin": 16, "result": "W", "predicted": 7.4, "pred_correct": true}, {"date": "1/6", "opponent": "Boston College High", "opp_slug": "boston-college-high", "opp_ma": true, "score": "35\u201338", "margin": -3, "result": "L", "predicted": -2.5, "pred_correct": true}, {"date": "1/9", "opponent": "Malden Catholic", "opp_slug": "malden-catholic", "opp_ma": true, "score": "54\u201359", "margin": -5, "result": "L", "predicted": -1.4, "pred_correct": true}, {"date": "1/13", "opponent": "Catholic Memorial", "opp_slug": "catholic-memorial", "opp_ma": true, "score": "73\u201358", "margin": 15, "result": "W", "predicted": 2.5, "pred_correct": true}, {"date": "1/16", "opponent": "St. John's Prep", "opp_slug": "st-john-s-prep", "opp_ma": true, "score": "58\u201362", "margin": -4, "result": "L", "predicted": 8.9, "pred_correct": false}, {"date": "1/20", "opponent": "Xaverian Brothers", "opp_slug": "xaverian-brothers", "opp_ma": true, "score": "61\u201367", "margin": -6, "result": "L", "predicted": -0.8, "pred_correct": true}, {"date": "1/23", "opponent": "Boston College High", "opp_slug": "boston-college-high", "opp_ma": true, "score": "44\u201362", "margin": -18, "result": "L", "predicted": -2.5, "pred_correct": true}, {"date": "1/30", "opponent": "Catholic Memorial", "opp_slug": "catholic-memorial", "opp_ma": true, "score": "62\u201347", "margin": 15, "result": "W", "predicted": 2.5, "pred_correct": true}, {"date": "2/1", "opponent": "Malden Catholic", "opp_slug": "malden-catholic", "opp_ma": true, "score": "57\u201363", "margin": -6, "result": "L", "predicted": -1.4, "pred_correct": true}, {"date": "2/3", "opponent": "St. John's Prep", "opp_slug": "st-john-s-prep", "opp_ma": true, "score": "52\u201343", "margin": 9, "result": "W", "predicted": 8.9, "pred_correct": true}, {"date": "2/6", "opponent": "Xaverian Brothers", "opp_slug": "xaverian-brothers", "opp_ma": true, "score": "56\u201355", "margin": 1, "result": "W", "predicted": -0.8, "pred_correct": false}, {"date": "2/10", "opponent": "Burncoat", "opp_slug": "burncoat", "opp_ma": true, "score": "77\u201357", "margin": 20, "result": "W", "predicted": 19.3, "pred_correct": true}, {"date": "2/13", "opponent": "Doherty Memorial", "opp_slug": "doherty-memorial", "opp_ma": true, "score": "65\u201352", "margin": 13, "result": "W", "predicted": 3.6, "pred_correct": true}, {"date": "2/16", "opponent": "Shrewsbury", "opp_slug": "shrewsbury", "opp_ma": true, "score": "62\u201374", "margin": -12, "result": "L", "predicted": 12.3, "pred_correct": false}, {"date": "2/18", "opponent": "Algonquin", "opp_slug": "algonquin", "opp_ma": true, "score": "50\u201346", "margin": 4, "result": "W", "predicted": 7.4, "pred_correct": true}]}