{"name": "Sizer School", "slug": "sizer-school", "gender": "boys", "rating": -26.775, "net_rank": 326, "total_teams": 358, "wins": 10, "losses": 10, "avg_margin": 2.55, "sos": -29.075, "sos_rank": 341, "sigma": 10.857, "pred_accuracy": 95.0, "schedule": [{"date": "12/12", "opponent": "Essex North Shore", "opp_slug": "essex-north-shore", "opp_ma": true, "score": "54\u201363", "margin": -9, "result": "L", "predicted": -9.4, "pred_correct": true}, {"date": "12/15", "opponent": "Trivium School", "opp_slug": "trivium-school", "opp_ma": true, "score": "53\u201324", "margin": 29, "result": "W", "predicted": 19.4, "pred_correct": true}, {"date": "12/16", "opponent": "Parker Charter School", "opp_slug": "parker-charter-school", "opp_ma": true, "score": "61\u201325", "margin": 36, "result": "W", "predicted": 22.4, "pred_correct": true}, {"date": "12/22", "opponent": "West Boylston", "opp_slug": "west-boylston", "opp_ma": true, "score": "44\u201340", "margin": 4, "result": "W", "predicted": -0.6, "pred_correct": false}, {"date": "1/5", "opponent": "Southbridge", "opp_slug": "southbridge", "opp_ma": true, "score": "54\u201360", "margin": -6, "result": "L", "predicted": -10.4, "pred_correct": true}, {"date": "1/14", "opponent": "Ayer Shirley", "opp_slug": "ayer-shirley", "opp_ma": true, "score": "46\u201354", "margin": -8, "result": "L", "predicted": -12.4, "pred_correct": true}, {"date": "1/16", "opponent": "Bethany Christian", "opp_slug": "bethany-christian", "opp_ma": true, "score": "39\u201370", "margin": -31, "result": "L", "predicted": -15.4, "pred_correct": true}, {"date": "1/20", "opponent": "South Lancaster Academy", "opp_slug": "south-lancaster-academy", "opp_ma": true, "score": "49\u201338", "margin": 11, "result": "W", "predicted": 10.2, "pred_correct": true}, {"date": "1/21", "opponent": "Trivium School", "opp_slug": "trivium-school", "opp_ma": true, "score": "51\u201327", "margin": 24, "result": "W", "predicted": 19.4, "pred_correct": true}, {"date": "1/23", "opponent": "North Brookfield", "opp_slug": "north-brookfield", "opp_ma": true, "score": "71\u201355", "margin": 16, "result": "W", "predicted": 16.8, "pred_correct": true}, {"date": "1/29", "opponent": "South Lancaster Academy", "opp_slug": "south-lancaster-academy", "opp_ma": true, "score": "62\u201338", "margin": 24, "result": "W", "predicted": 10.2, "pred_correct": true}, {"date": "2/2", "opponent": "Bethany Christian", "opp_slug": "bethany-christian", "opp_ma": true, "score": "42\u201358", "margin": -16, "result": "L", "predicted": -15.4, "pred_correct": true}, {"date": "2/5", "opponent": "Abby Kelley Foster", "opp_slug": "abby-kelley-foster", "opp_ma": true, "score": "44\u201355", "margin": -11, "result": "L", "predicted": -1.5, "pred_correct": true}, {"date": "2/6", "opponent": "North Brookfield", "opp_slug": "north-brookfield", "opp_ma": true, "score": "66\u201344", "margin": 22, "result": "W", "predicted": 16.8, "pred_correct": true}, {"date": "2/9", "opponent": "South Lancaster Academy", "opp_slug": "south-lancaster-academy", "opp_ma": true, "score": "53\u201346", "margin": 7, "result": "W", "predicted": 10.2, "pred_correct": true}, {"date": "2/11", "opponent": "Bethany Christian", "opp_slug": "bethany-christian", "opp_ma": true, "score": "48\u201361", "margin": -13, "result": "L", "predicted": -15.4, "pred_correct": true}, {"date": "2/12", "opponent": "Parker Charter School", "opp_slug": "parker-charter-school", "opp_ma": true, "score": "52\u201339", "margin": 13, "result": "W", "predicted": 22.4, "pred_correct": true}, {"date": "2/13", "opponent": "Essex North Shore", "opp_slug": "essex-north-shore", "opp_ma": true, "score": "47\u201355", "margin": -8, "result": "L", "predicted": -9.4, "pred_correct": true}, {"date": "2/16", "opponent": "Southbridge", "opp_slug": "southbridge", "opp_ma": true, "score": "44\u201366", "margin": -22, "result": "L", "predicted": -10.4, "pred_correct": true}, {"date": "2/17", "opponent": "Abby Kelley Foster", "opp_slug": "abby-kelley-foster", "opp_ma": true, "score": "41\u201352", "margin": -11, "result": "L", "predicted": -1.5, "pred_correct": true}]}