{"name": "Avon", "slug": "avon", "gender": "girls", "rating": -42.366, "net_rank": 334, "total_teams": 352, "wins": 1, "losses": 15, "avg_margin": -24.88, "sos": -19.869, "sos_rank": 272, "sigma": 11.022, "pred_accuracy": 93.8, "schedule": [{"date": "12/11", "opponent": "Atlantis Charter", "opp_slug": "atlantis-charter", "opp_ma": true, "score": "14\u201341", "margin": -27, "result": "L", "predicted": -25.2, "pred_correct": true}, {"date": "12/17", "opponent": "Randolph", "opp_slug": "randolph", "opp_ma": true, "score": "18\u201347", "margin": -29, "result": "L", "predicted": -21.3, "pred_correct": true}, {"date": "12/19", "opponent": "South Shore VT", "opp_slug": "south-shore-vt", "opp_ma": true, "score": "26\u201320", "margin": 6, "result": "W", "predicted": 6.2, "pred_correct": true}, {"date": "12/30", "opponent": "Old Colony RVT", "opp_slug": "old-colony-rvt", "opp_ma": true, "score": "26\u201346", "margin": -20, "result": "L", "predicted": -19.3, "pred_correct": true}, {"date": "1/5", "opponent": "Bristol County Agricultural", "opp_slug": "bristol-county-agricultural", "opp_ma": true, "score": "7\u201325", "margin": -18, "result": "L", "predicted": -4.1, "pred_correct": true}, {"date": "1/7", "opponent": "Holbrook", "opp_slug": "holbrook", "opp_ma": true, "score": "17\u201349", "margin": -32, "result": "L", "predicted": -42.0, "pred_correct": true}, {"date": "1/13", "opponent": "Westport", "opp_slug": "westport", "opp_ma": true, "score": "25\u201348", "margin": -23, "result": "L", "predicted": -28.3, "pred_correct": true}, {"date": "1/15", "opponent": "Atlantis Charter", "opp_slug": "atlantis-charter", "opp_ma": true, "score": "11\u201353", "margin": -42, "result": "L", "predicted": -25.2, "pred_correct": true}, {"date": "1/20", "opponent": "Wareham", "opp_slug": "wareham", "opp_ma": true, "score": "7\u201343", "margin": -36, "result": "L", "predicted": -40.3, "pred_correct": true}, {"date": "1/21", "opponent": "St. Mary Parish (Westfield)", "opp_slug": "st-mary-parish-westfield", "opp_ma": true, "score": "30\u201346", "margin": -16, "result": "L", "predicted": -15.5, "pred_correct": true}, {"date": "1/29", "opponent": "Westport", "opp_slug": "westport", "opp_ma": true, "score": "24\u201348", "margin": -24, "result": "L", "predicted": -28.3, "pred_correct": true}, {"date": "2/2", "opponent": "Holbrook", "opp_slug": "holbrook", "opp_ma": true, "score": "20\u201357", "margin": -37, "result": "L", "predicted": -42.0, "pred_correct": true}, {"date": "2/4", "opponent": "Wareham", "opp_slug": "wareham", "opp_ma": true, "score": "14\u201345", "margin": -31, "result": "L", "predicted": -40.3, "pred_correct": true}, {"date": "2/6", "opponent": "Randolph", "opp_slug": "randolph", "opp_ma": true, "score": "14\u201334", "margin": -20, "result": "L", "predicted": -21.3, "pred_correct": true}, {"date": "2/11", "opponent": "South Shore VT", "opp_slug": "south-shore-vt", "opp_ma": true, "score": "19\u201328", "margin": -9, "result": "L", "predicted": 6.2, "pred_correct": false}, {"date": "2/13", "opponent": "Old Colony RVT", "opp_slug": "old-colony-rvt", "opp_ma": true, "score": "16\u201356", "margin": -40, "result": "L", "predicted": -19.3, "pred_correct": true}]}