{"name": "Boston Preparatory", "slug": "boston-preparatory", "gender": "girls", "rating": -39.714, "net_rank": 330, "total_teams": 352, "wins": 2, "losses": 10, "avg_margin": -23.08, "sos": -22.8, "sos_rank": 288, "sigma": 11.022, "pred_accuracy": 75.0, "schedule": [{"date": "12/12", "opponent": "Edward M. Kennedy Acad.", "opp_slug": "edward-m-kennedy-acad", "opp_ma": true, "score": "22\u201326", "margin": -4, "result": "L", "predicted": 0.2, "pred_correct": false}, {"date": "12/16", "opponent": "Prospect Hill Academy", "opp_slug": "prospect-hill-academy", "opp_ma": true, "score": "16\u201363", "margin": -47, "result": "L", "predicted": -32.2, "pred_correct": true}, {"date": "1/2", "opponent": "Neighborhood House", "opp_slug": "neighborhood-house", "opp_ma": true, "score": "24\u201353", "margin": -29, "result": "L", "predicted": -32.3, "pred_correct": true}, {"date": "1/7", "opponent": "Argosy Collegiate Charter", "opp_slug": "argosy-collegiate-charter", "opp_ma": true, "score": "23\u201338", "margin": -15, "result": "L", "predicted": -4.7, "pred_correct": true}, {"date": "1/8", "opponent": "Codman Academy", "opp_slug": "codman-academy", "opp_ma": true, "score": "20\u201327", "margin": -7, "result": "L", "predicted": -1.0, "pred_correct": true}, {"date": "1/12", "opponent": "New Heights Charter", "opp_slug": "new-heights-charter", "opp_ma": true, "score": "18\u201361", "margin": -43, "result": "L", "predicted": -38.4, "pred_correct": true}, {"date": "1/22", "opponent": "Brooke Charter", "opp_slug": "brooke-charter", "opp_ma": true, "score": "6\u201375", "margin": -69, "result": "L", "predicted": -25.2, "pred_correct": true}, {"date": "1/29", "opponent": "South Shore Charter", "opp_slug": "south-shore-charter", "opp_ma": true, "score": "33\u201348", "margin": -15, "result": "L", "predicted": -7.1, "pred_correct": true}, {"date": "1/30", "opponent": "Foxborough Charter", "opp_slug": "foxborough-charter", "opp_ma": true, "score": "31\u201328", "margin": 3, "result": "W", "predicted": -4.4, "pred_correct": false}, {"date": "2/2", "opponent": "Roxbury Prep Charter", "opp_slug": "roxbury-prep-charter", "opp_ma": true, "score": "39\u201335", "margin": 4, "result": "W", "predicted": -4.0, "pred_correct": false}, {"date": "2/3", "opponent": "Boston Collegiate Charter", "opp_slug": "boston-collegiate-charter", "opp_ma": true, "score": "15\u201335", "margin": -20, "result": "L", "predicted": -21.5, "pred_correct": true}, {"date": "2/18", "opponent": "Prospect Hill Academy", "opp_slug": "prospect-hill-academy", "opp_ma": true, "score": "14\u201349", "margin": -35, "result": "L", "predicted": -32.2, "pred_correct": true}]}