{"name": "Smith VT", "slug": "smith-vt", "gender": "girls", "rating": -18.041, "net_rank": 259, "total_teams": 352, "wins": 12, "losses": 8, "avg_margin": 5.8, "sos": -23.743, "sos_rank": 295, "sigma": 11.022, "pred_accuracy": 90.0, "schedule": [{"date": "12/16", "opponent": "Pathfinder RVT", "opp_slug": "pathfinder-rvt", "opp_ma": true, "score": "49\u201330", "margin": 19, "result": "W", "predicted": 10.0, "pred_correct": true}, {"date": "12/18", "opponent": "Franklin County Tech", "opp_slug": "franklin-county-tech", "opp_ma": true, "score": "38\u201333", "margin": 5, "result": "W", "predicted": 7.5, "pred_correct": true}, {"date": "12/19", "opponent": "Turners Falls", "opp_slug": "turners-falls", "opp_ma": true, "score": "51\u201321", "margin": 30, "result": "W", "predicted": 27.0, "pred_correct": true}, {"date": "1/2", "opponent": "Putnam VT", "opp_slug": "putnam-vt", "opp_ma": true, "score": "62\u201344", "margin": 18, "result": "W", "predicted": 2.0, "pred_correct": true}, {"date": "1/5", "opponent": "Lenox Memorial", "opp_slug": "lenox-memorial", "opp_ma": true, "score": "29\u201347", "margin": -18, "result": "L", "predicted": -16.9, "pred_correct": true}, {"date": "1/7", "opponent": "Mohawk Trail Regional", "opp_slug": "mohawk-trail-regional", "opp_ma": true, "score": "39\u201329", "margin": 10, "result": "W", "predicted": 1.3, "pred_correct": true}, {"date": "1/9", "opponent": "Athol", "opp_slug": "athol", "opp_ma": true, "score": "34\u201325", "margin": 9, "result": "W", "predicted": 16.1, "pred_correct": true}, {"date": "1/12", "opponent": "John J. Duggan Academy", "opp_slug": "john-j-duggan-academy", "opp_ma": true, "score": "47\u201332", "margin": 15, "result": "W", "predicted": 19.9, "pred_correct": true}, {"date": "1/15", "opponent": "Pathfinder RVT", "opp_slug": "pathfinder-rvt", "opp_ma": true, "score": "37\u201347", "margin": -10, "result": "L", "predicted": 10.0, "pred_correct": false}, {"date": "1/20", "opponent": "Easthampton", "opp_slug": "easthampton", "opp_ma": true, "score": "39\u201341", "margin": -2, "result": "L", "predicted": -19.0, "pred_correct": true}, {"date": "1/22", "opponent": "Turners Falls", "opp_slug": "turners-falls", "opp_ma": true, "score": "60\u201328", "margin": 32, "result": "W", "predicted": 27.0, "pred_correct": true}, {"date": "1/23", "opponent": "Hampden Charter of Science", "opp_slug": "hampden-charter-of-science", "opp_ma": true, "score": "43\u201327", "margin": 16, "result": "W", "predicted": 19.8, "pred_correct": true}, {"date": "1/29", "opponent": "Putnam VT", "opp_slug": "putnam-vt", "opp_ma": true, "score": "48\u201358", "margin": -10, "result": "L", "predicted": 2.0, "pred_correct": false}, {"date": "2/2", "opponent": "Pioneer Valley Regional", "opp_slug": "pioneer-valley-regional", "opp_ma": true, "score": "33\u201351", "margin": -18, "result": "L", "predicted": -2.3, "pred_correct": true}, {"date": "2/4", "opponent": "John J. Duggan Academy", "opp_slug": "john-j-duggan-academy", "opp_ma": true, "score": "40\u201330", "margin": 10, "result": "W", "predicted": 19.9, "pred_correct": true}, {"date": "2/5", "opponent": "Athol", "opp_slug": "athol", "opp_ma": true, "score": "53\u201327", "margin": 26, "result": "W", "predicted": 16.1, "pred_correct": true}, {"date": "2/9", "opponent": "Baystate Academy", "opp_slug": "baystate-academy", "opp_ma": true, "score": "41\u201348", "margin": -7, "result": "L", "predicted": -8.3, "pred_correct": true}, {"date": "2/10", "opponent": "Baystate Academy", "opp_slug": "baystate-academy", "opp_ma": true, "score": "40\u201346", "margin": -6, "result": "L", "predicted": -8.3, "pred_correct": true}, {"date": "2/12", "opponent": "HS of Science & Technology", "opp_slug": "hs-of-science-technology", "opp_ma": true, "score": "67\u201344", "margin": 23, "result": "W", "predicted": 1.6, "pred_correct": true}, {"date": "2/13", "opponent": "Holyoke", "opp_slug": "holyoke", "opp_ma": true, "score": "28\u201354", "margin": -26, "result": "L", "predicted": -11.3, "pred_correct": true}]}